google_play_scraper/__init__.py
google_play_scraper/constants/__init__.py
google_play_scraper/constants/element.py
google_play_scraper/constants/google_play.py
google_play_scraper/constants/regex.py
google_play_scraper/constants/request.py
google_play_scraper/exceptions.py
google_play_scraper/features/__init__.py
google_play_scraper/features/app.py
google_play_scraper/features/permissions.py
google_play_scraper/features/reviews.py
google_play_scraper/features/search.py
google_play_scraper/utils/__init__.py
google_play_scraper/utils/data_processors.py
google_play_scraper/utils/request.py
google_play_scraper-1.2.5.dist-info/LICENSE
google_play_scraper-1.2.5.dist-info/METADATA
google_play_scraper-1.2.5.dist-info/WHEEL
google_play_scraper-1.2.5.dist-info/RECORD
